odoo9_addon_l10n_ch_bank_statement_import_postfinance-9.0.1.0.1-py2.7-nspkg.pth
odoo9_addon_l10n_ch_bank_statement_import_postfinance-9.0.1.0.1.dist-info/DESCRIPTION.rst
odoo9_addon_l10n_ch_bank_statement_import_postfinance-9.0.1.0.1.dist-info/METADATA
odoo9_addon_l10n_ch_bank_statement_import_postfinance-9.0.1.0.1.dist-info/RECORD
odoo9_addon_l10n_ch_bank_statement_import_postfinance-9.0.1.0.1.dist-info/WHEEL
odoo9_addon_l10n_ch_bank_statement_import_postfinance-9.0.1.0.1.dist-info/metadata.json
odoo9_addon_l10n_ch_bank_statement_import_postfinance-9.0.1.0.1.dist-info/namespace_packages.txt
odoo9_addon_l10n_ch_bank_statement_import_postfinance-9.0.1.0.1.dist-info/top_level.txt
odoo_addons/l10n_ch_bank_statement_import_postfinance/README.rst
odoo_addons/l10n_ch_bank_statement_import_postfinance/__init__.py
odoo_addons/l10n_ch_bank_statement_import_postfinance/__openerp__.py
odoo_addons/l10n_ch_bank_statement_import_postfinance/i18n/ca.po
odoo_addons/l10n_ch_bank_statement_import_postfinance/i18n/ca_ES.po
odoo_addons/l10n_ch_bank_statement_import_postfinance/i18n/de.po
odoo_addons/l10n_ch_bank_statement_import_postfinance/i18n/es.po
odoo_addons/l10n_ch_bank_statement_import_postfinance/i18n/fi.po
odoo_addons/l10n_ch_bank_statement_import_postfinance/i18n/fr.po
odoo_addons/l10n_ch_bank_statement_import_postfinance/i18n/fr_CH.po
odoo_addons/l10n_ch_bank_statement_import_postfinance/i18n/gl.po
odoo_addons/l10n_ch_bank_statement_import_postfinance/i18n/hr_HR.po
odoo_addons/l10n_ch_bank_statement_import_postfinance/i18n/hu.po
odoo_addons/l10n_ch_bank_statement_import_postfinance/i18n/it.po
odoo_addons/l10n_ch_bank_statement_import_postfinance/i18n/lt_LT.po
odoo_addons/l10n_ch_bank_statement_import_postfinance/i18n/nb_NO.po
odoo_addons/l10n_ch_bank_statement_import_postfinance/i18n/nl.po
odoo_addons/l10n_ch_bank_statement_import_postfinance/i18n/nl_NL.po
odoo_addons/l10n_ch_bank_statement_import_postfinance/i18n/pt_BR.po
odoo_addons/l10n_ch_bank_statement_import_postfinance/i18n/pt_PT.po
odoo_addons/l10n_ch_bank_statement_import_postfinance/i18n/sl.po
odoo_addons/l10n_ch_bank_statement_import_postfinance/i18n/tr.po
odoo_addons/l10n_ch_bank_statement_import_postfinance/migrations/9.0.1.0.0/post-migration.py
odoo_addons/l10n_ch_bank_statement_import_postfinance/models/__init__.py
odoo_addons/l10n_ch_bank_statement_import_postfinance/models/account_bank_statement_line.py
odoo_addons/l10n_ch_bank_statement_import_postfinance/models/postfinance_file_parser.py
