Metadata-Version: 2.0
Name: odoo9-addon-l10n-ch-bank-statement-import-postfinance
Version: 9.0.1.0.1
Summary: Swiss bank statements import
Home-page: http://www.compassion.ch/
Author: Compassion CH, Camptocamp, Odoo Community Association (OCA)
Author-email: support@odoo-community.org
License: AGPL-3
Platform: UNKNOWN
Classifier: Programming Language :: Python
Classifier: Framework :: Odoo
Classifier: License :: OSI Approved :: GNU Affero General Public License v3
Requires-Python: ~=2.7
Requires-Dist: odoo (<9.1a,>=9.0a)
Requires-Dist: odoo9-addon-account-bank-statement-import-camt
Requires-Dist: wand
Requires-Dist: xlrd
